pytq_crawlib/__init__.py
pytq_crawlib/__init__.pyc
pytq_crawlib/scheduler.py
pytq_crawlib/scheduler.pyc
pytq_crawlib/__pycache__/__init__.cpython-34.pyc
pytq_crawlib/__pycache__/__init__.cpython-35.pyc
pytq_crawlib/__pycache__/__init__.cpython-36.pyc
pytq_crawlib/__pycache__/scheduler.cpython-34.pyc
pytq_crawlib/__pycache__/scheduler.cpython-35.pyc
pytq_crawlib/__pycache__/scheduler.cpython-36.pyc
pytq_crawlib-0.0.6.dist-info/DESCRIPTION.rst
pytq_crawlib-0.0.6.dist-info/METADATA
pytq_crawlib-0.0.6.dist-info/RECORD
pytq_crawlib-0.0.6.dist-info/WHEEL
pytq_crawlib-0.0.6.dist-info/metadata.json
pytq_crawlib-0.0.6.dist-info/top_level.txt
