Metadata-Version: 2.0
Name: pytq-crawlib
Version: 0.0.6
Summary: UNKNOWN
Home-page: https://github.com/MacHu-GWU/
Author: Sanhe Hu
Author-email: husanhe@gmail.com
License: MIT
Download-URL: https://pypi.python.org/pypi/pytq_crawlib/0.0.6#downloads
Platform: Windows
Platform: MacOS
Platform: Unix
Classifier: Development Status :: 4 - Beta
Classifier: Intended Audience :: Developers
Classifier: License :: OSI Approved :: MIT License
Classifier: Natural Language :: English
Classifier: Operating System :: Microsoft :: Windows
Classifier: Operating System :: MacOS
Classifier: Operating System :: Unix
Classifier: Programming Language :: Python
Classifier: Programming Language :: Python :: 2.7
Classifier: Programming Language :: Python :: 3.4
Classifier: Programming Language :: Python :: 3.5
Classifier: Programming Language :: Python :: 3.6
Requires-Dist: attrs-mate
Requires-Dist: loggerFactory (>=0.0.4)
Requires-Dist: crawlib (>=0.0.15)
Requires-Dist: pytq (>=0.0.7)
Requires-Dist: pathlib-mate
Requires-Dist: pymongo-mate
Requires-Dist: mongoengine-mate
Requires-Dist: sfm (>=0.0.15)
